pdyna/__init__.py
pdyna/_version.py
pdyna/analysis.py
pdyna/core.py
pdyna/io.py
pdyna/structural.py
pdyna/basis/octahedron_basis.json
pdyna/basis/octahedron_basis_analytical.json
pdyna/basis/octahedron_basis_full.json
pdyna-1.1.1.data/data/LICENSE
pdyna-1.1.1.dist-info/LICENSE
pdyna-1.1.1.dist-info/METADATA
pdyna-1.1.1.dist-info/WHEEL
pdyna-1.1.1.dist-info/top_level.txt
pdyna-1.1.1.dist-info/RECORD
