Metadata-Version: 2.1
Name: pdyna
Version: 1.1.1
Summary: Perovskite dynamics analysis package
Home-page: https://github.com/WMD-group/PDynA
Author: Xia Liang
Author-email: Xia Liang <xia.liang16@imperial.ac.uk>
License: MIT License
Project-URL: Homepage, https://pdyna.readthedocs.io/en/latest/
Project-URL: Documentation, https://pdyna.readthedocs.io/en/latest/
Project-URL: Package, https://pypi.org/project/pdyna/
Project-URL: Repository, https://github.com/WMD-group/PDynA
Classifier: License :: OSI Approved :: MIT License
Classifier: Programming Language :: Python :: 3
Classifier: Intended Audience :: Science/Research
Classifier: Operating System :: OS Independent
Classifier: Topic :: Scientific/Engineering :: Information Analysis
Classifier: Topic :: Software Development :: Libraries :: Python Modules
Requires-Python: >=3.8
License-File: LICENSE
Requires-Dist: numpy
Requires-Dist: matplotlib
Requires-Dist: pymatgen
Requires-Dist: ase
Requires-Dist: scipy
Provides-Extra: datasets
Requires-Dist: pymlff; extra == "datasets"
Provides-Extra: docs
Requires-Dist: sphinx; extra == "docs"
Requires-Dist: sphinx-book-theme; extra == "docs"
Requires-Dist: sphinx-design; extra == "docs"
Provides-Extra: pdf
Requires-Dist: pycairo; extra == "pdf"
